picowrap/__init__.py
picowrap/cbase.py
picowrap/channel.py
picowrap/constants.py
picowrap/errors.py
picowrap/picoscope.py
picowrap-0.1.1.dist-info/LICENSE
picowrap-0.1.1.dist-info/WHEEL
picowrap-0.1.1.dist-info/METADATA
picowrap-0.1.1.dist-info/RECORD
