Metadata-Version: 2.1
Name: picowrap
Version: 0.1.1
Summary: Picoscope SDK wrapper for python 
Author: ymosteiro
Requires-Python: >=3.10
Classifier: License :: OSI Approved :: MIT License
Requires-Dist: black >= 21.1.0 ; extra == "dev"
Requires-Dist: pylint >= 2.12.2 ; extra == "dev"
Requires-Dist: isort >= 5.10.1 ; extra == "dev"
Requires-Dist: matplotlib >=  3.5.0 ; extra == "dev"
Provides-Extra: dev
